LICENSE
MANIFEST.in
README.md
requirements.txt
setup.cfg
setup.py
lsmpy/__init__.py
lsmpy/lsmpy.py
lsmpy.egg-info/PKG-INFO
lsmpy.egg-info/SOURCES.txt
lsmpy.egg-info/dependency_links.txt
lsmpy.egg-info/not-zip-safe
lsmpy.egg-info/top_level.txt