Metadata-Version: 2.1
Name: lsmpy
Version: 0.0.1
Summary: A demo python package
Home-page: https://github.com/SASM235/lsmpy
Author: Shruti Anna Samuel
Author-email: annasam13@gmail.com
License: MIT license
Keywords: lsmpy
Platform: UNKNOWN
Classifier: Development Status :: 2 - Pre-Alpha
Classifier: Intended Audience :: Developers
Classifier: License :: OSI Approved :: MIT License
Classifier: Natural Language :: English
Classifier: Programming Language :: Python :: 3
Classifier: Programming Language :: Python :: 3.5
Classifier: Programming Language :: Python :: 3.6
Classifier: Programming Language :: Python :: 3.7
Classifier: Programming Language :: Python :: 3.8
Requires-Python: >=3.5
